README.md
solid_mcad/MCAD/.git
solid_mcad/MCAD/PyOpenScad/PyOpenSCAD_docs.txt
solid_mcad/MCAD/PyOpenScad/TODO_PyOpenScad.txt
solid_mcad/MCAD/PyOpenScad/arc_scad.py
solid_mcad/MCAD/PyOpenScad/examples/basic_scad_include.py
solid_mcad/MCAD/PyOpenScad/examples/mazebox/inset.py
solid_mcad/MCAD/PyOpenScad/examples/mazebox/mazebox_clean2_stable.py
solid_mcad/MCAD/PyOpenScad/examples/mazebox/testpng.py
solid_mcad/MCAD/PyOpenScad/examples/mazebox/trianglemath.py
solid_mcad/MCAD/PyOpenScad/examples/playground/maze7.png
solid_mcad/MCAD/PyOpenScad/examples/sierpinski.py
solid_mcad/MCAD/PyOpenScad/pyopenscad.py
solid_mcad/MCAD/PyOpenScad/scratch/test_include.scad
solid_mcad/MCAD/PyOpenScad/scratch/test_pos.py
solid_mcad/MCAD/PyOpenScad/scratch/test_scad_include.py
solid_mcad/MCAD/PyOpenScad/scratch/test_scad_parse.py
solid_mcad/MCAD/README.markdown
solid_mcad/MCAD/TODO
solid_mcad/MCAD/__init__.py
solid_mcad/MCAD/bearing.scad
solid_mcad/MCAD/bitmap/README
solid_mcad/MCAD/bitmap/alphabet_block.scad
solid_mcad/MCAD/bitmap/bitmap.scad
solid_mcad/MCAD/bitmap/height_map.scad
solid_mcad/MCAD/bitmap/letter_necklace.scad
solid_mcad/MCAD/bitmap/name_tag.scad
solid_mcad/MCAD/boxes.scad
solid_mcad/MCAD/constants.scad
solid_mcad/MCAD/curves.scad
solid_mcad/MCAD/gears.scad
solid_mcad/MCAD/gridbeam.scad
solid_mcad/MCAD/hardware.scad
solid_mcad/MCAD/involute_gears.scad
solid_mcad/MCAD/lgpl-2.1.txt
solid_mcad/MCAD/materials.scad
solid_mcad/MCAD/math.scad
solid_mcad/MCAD/metric_fastners.scad
solid_mcad/MCAD/motors.scad
solid_mcad/MCAD/nuts_and_bolts.scad
solid_mcad/MCAD/openscad_testing.py
solid_mcad/MCAD/openscad_utils.py
solid_mcad/MCAD/regular_shapes.scad
solid_mcad/MCAD/screw.scad
solid_mcad/MCAD/servos.scad
solid_mcad/MCAD/shapes.scad
solid_mcad/MCAD/stepper.scad
solid_mcad/MCAD/teardrop.scad
solid_mcad/MCAD/test_docs.py
solid_mcad/MCAD/test_mcad.py
solid_mcad/MCAD/triangles.scad
solid_mcad/MCAD/units.scad
solid_mcad/MCAD/utilities.scad
solid_mcad/__init__.py
solid_mcad-0.1.1.dist-info/WHEEL
solid_mcad-0.1.1.dist-info/METADATA
solid_mcad-0.1.1.dist-info/RECORD
