Metadata-Version: 2.1
Name: solid-mcad
Version: 0.1.1
Summary: Python binding for the OpenSCAD language utility library, MCAD
Author: Evan Jones
Author-email: evan_t_jones@mac.com
Requires-Python: >=3.7,<4.0
Classifier: Programming Language :: Python :: 3
Classifier: Programming Language :: Python :: 3.7
Requires-Dist: solidpython (>=0.3.2)
